[{
        "model": "api.movie",
        "pk": 1,
        "fields": {
            "created_at": "2021-01-04T07:03:36.237Z",
            "order": 1,
            "package": 2,
            "state": "P",
            "title": "Deadpool1",
            "link": "http://google1.com",
            "runtime": 8.0,
            "about": "",
            "lang": 1,
            "poster": "/media/posters/0000000004.png",
            "month": null,
            "publish_on": "2021-01-01T08:50:47Z",
            "jury_rating": 0.0,
            "audience_rating": 0.0,
            "recommend_count": 2,
            "review_count": 0,
            "approved": true,
            "genres": [
                1
            ]
        }
    },
    {
        "model": "api.movie",
        "pk": 2,
        "fields": {
            "created_at": "2021-01-04T07:03:36.237Z",
            "order": 1,
            "package": 2,
            "state": "P",
            "title": "Deadpool2",
            "link": "http://google2.com",
            "runtime": 8.0,
            "about": "",
            "lang": 1,
            "poster": "/media/posters/0000000004.png",
            "month": null,
            "publish_on": "2021-01-10T08:50:47Z",
            "jury_rating": 0.0,
            "audience_rating": 0.0,
            "recommend_count": 2,
            "review_count": 0,
            "approved": true,
            "genres": [
                1
            ]
        }
    },
    {
        "model": "api.movie",
        "pk": 3,
        "fields": {
            "created_at": "2021-01-04T07:03:36.237Z",
            "order": 1,
            "package": 2,
            "state": "P",
            "title": "Deadpool3",
            "link": "http://google3.com",
            "runtime": 8.0,
            "about": "",
            "lang": 1,
            "poster": "/media/posters/0000000004.png",
            "month": null,
            "publish_on": "2021-01-20T08:50:47Z",
            "jury_rating": 0.0,
            "audience_rating": 0.0,
            "recommend_count": 2,
            "review_count": 0,
            "approved": true,
            "genres": [
                1
            ]
        }
    },
    {
        "model": "api.movie",
        "pk": 4,
        "fields": {
            "created_at": "2021-01-04T07:03:36.237Z",
            "order": 1,
            "package": 2,
            "state": "P",
            "title": "Deadpool4",
            "link": "http://google4com",
            "runtime": 8.0,
            "about": "",
            "lang": 1,
            "poster": "/media/posters/0000000004.png",
            "month": null,
            "publish_on": "2021-01-30T08:50:47Z",
            "jury_rating": 0.0,
            "audience_rating": 0.0,
            "recommend_count": 2,
            "review_count": 0,
            "approved": true,
            "genres": [
                1
            ]
        }
    },
    {
        "model": "api.movie",
        "pk": 5,
        "fields": {
            "created_at": "2021-01-04T07:03:36.237Z",
            "order": 1,
            "package": 2,
            "state": "P",
            "title": "Deadpool5",
            "link": "http://google5.com",
            "runtime": 8.0,
            "about": "",
            "lang": 1,
            "poster": "/media/posters/0000000004.png",
            "month": null,
            "publish_on": "2021-02-01T08:50:47Z",
            "jury_rating": 0.0,
            "audience_rating": 0.0,
            "recommend_count": 2,
            "review_count": 0,
            "approved": true,
            "genres": [
                1
            ]
        }
    },
    {
        "model": "api.movie",
        "pk": 6,
        "fields": {
            "created_at": "2021-01-04T07:03:36.237Z",
            "order": 1,
            "package": 2,
            "state": "P",
            "title": "Deadpool6",
            "link": "http://google6.com",
            "runtime": 8.0,
            "about": "",
            "lang": 1,
            "poster": "/media/posters/0000000004.png",
            "month": null,
            "publish_on": "2021-02-10T08:50:47Z",
            "jury_rating": 0.0,
            "audience_rating": 0.0,
            "recommend_count": 2,
            "review_count": 0,
            "approved": true,
            "genres": [
                1
            ]
        }
    },
    {
        "model": "api.movie",
        "pk": 7,
        "fields": {
            "created_at": "2021-01-04T07:03:36.237Z",
            "order": 1,
            "package": 2,
            "state": "P",
            "title": "Deadpool7",
            "link": "http://google7.com",
            "runtime": 8.0,
            "about": "",
            "lang": 1,
            "poster": "/media/posters/0000000004.png",
            "month": null,
            "publish_on": "2021-02-20T08:50:47Z",
            "jury_rating": 0.0,
            "audience_rating": 0.0,
            "recommend_count": 2,
            "review_count": 0,
            "approved": true,
            "genres": [
                1
            ]
        }
    },
    {
        "model": "api.movie",
        "pk": 8,
        "fields": {
            "created_at": "2021-01-04T07:03:36.237Z",
            "order": 1,
            "package": 2,
            "state": "P",
            "title": "Deadpool8",
            "link": "http://google8.com",
            "runtime": 8.0,
            "about": "",
            "lang": 1,
            "poster": "/media/posters/0000000004.png",
            "month": null,
            "publish_on": "2021-03-01T08:50:47Z",
            "jury_rating": 0.0,
            "audience_rating": 0.0,
            "recommend_count": 2,
            "review_count": 0,
            "approved": true,
            "genres": [
                1
            ]
        }
    },
    {
        "model": "api.movie",
        "pk": 9,
        "fields": {
            "created_at": "2021-01-04T07:03:36.237Z",
            "order": 1,
            "package": 2,
            "state": "P",
            "title": "Deadpool9",
            "link": "http://google9.com",
            "runtime": 8.0,
            "about": "",
            "lang": 1,
            "poster": "/media/posters/0000000004.png",
            "month": null,
            "publish_on": "2021-03-10T08:50:47Z",
            "jury_rating": 0.0,
            "audience_rating": 0.0,
            "recommend_count": 2,
            "review_count": 0,
            "approved": true,
            "genres": [
                1
            ]
        }
    },
    {
        "model": "api.movie",
        "pk": 10,
        "fields": {
            "created_at": "2021-01-04T07:03:36.237Z",
            "order": 1,
            "package": 2,
            "state": "P",
            "title": "Deadpool10",
            "link": "http://google10.com",
            "runtime": 8.0,
            "about": "",
            "lang": 1,
            "poster": "/media/posters/0000000004.png",
            "month": null,
            "publish_on": "2021-03-20T08:50:47Z",
            "jury_rating": 0.0,
            "audience_rating": 0.0,
            "recommend_count": 2,
            "review_count": 0,
            "approved": true,
            "genres": [
                1
            ]
        }
    },
    {
        "model": "api.movie",
        "pk": 11,
        "fields": {
            "created_at": "2021-01-04T07:03:36.237Z",
            "order": 1,
            "package": 2,
            "state": "P",
            "title": "Deadpool11",
            "link": "http://google11.com",
            "runtime": 8.0,
            "about": "",
            "lang": 1,
            "poster": "/media/posters/0000000004.png",
            "month": null,
            "publish_on": "2021-03-20T08:50:47Z",
            "jury_rating": 0.0,
            "audience_rating": 0.0,
            "recommend_count": 2,
            "review_count": 0,
            "approved": true,
            "genres": [
                1
            ]
        }
    },
    {
        "model": "api.crewmember",
        "pk": 1,
        "fields": {
            "movie": 1,
            "profile": 1,
            "role": 2
        }
    },
    {
        "model": "api.crewmember",
        "pk": 2,
        "fields": {
            "movie": 2,
            "profile": 1,
            "role": 2
        }
    },
    {
        "model": "api.crewmember",
        "pk": 3,
        "fields": {
            "movie": 3,
            "profile": 1,
            "role": 2
        }
    },
    {
        "model": "api.crewmember",
        "pk": 4,
        "fields": {
            "movie": 4,
            "profile": 1,
            "role": 2
        }
    },
    {
        "model": "api.crewmember",
        "pk": 5,
        "fields": {
            "movie": 5,
            "profile": 1,
            "role": 2
        }
    },
    {
        "model": "api.crewmember",
        "pk": 6,
        "fields": {
            "movie": 6,
            "profile": 1,
            "role": 2
        }
    },
    {
        "model": "api.crewmember",
        "pk": 7,
        "fields": {
            "movie": 7,
            "profile": 1,
            "role": 2
        }
    },
    {
        "model": "api.crewmember",
        "pk": 8,
        "fields": {
            "movie": 8,
            "profile": 1,
            "role": 2
        }
    },
    {
        "model": "api.crewmember",
        "pk": 9,
        "fields": {
            "movie": 9,
            "profile": 1,
            "role": 2
        }
    },
    {
        "model": "api.crewmember",
        "pk": 10,
        "fields": {
            "movie": 10,
            "profile": 1,
            "role": 2
        }
    },
    {
        "model": "api.crewmember",
        "pk": 11,
        "fields": {
            "movie": 11,
            "profile": 1,
            "role": 2
        }
    },
    {
        "model": "api.movielist_movies",
        "pk": 1,
        "fields": {
            "movielist": 1,
            "movie": 1
        }
    },
    {
        "model": "api.movielist_movies",
        "pk": 2,
        "fields": {
            "movielist": 1,
            "movie": 2
        }
    },
    {
        "model": "api.movielist_movies",
        "pk": 3,
        "fields": {
            "movielist": 1,
            "movie": 3
        }
    },
    {
        "model": "api.movielist_movies",
        "pk": 4,
        "fields": {
            "movielist": 1,
            "movie": 4
        }
    },
    {
        "model": "api.movielist_movies",
        "pk": 5,
        "fields": {
            "movielist": 1,
            "movie": 5
        }
    },
    {
        "model": "api.movielist_movies",
        "pk": 6,
        "fields": {
            "movielist": 1,
            "movie": 6
        }
    },
    {
        "model": "api.movielist_movies",
        "pk": 7,
        "fields": {
            "movielist": 1,
            "movie": 7
        }
    },
    {
        "model": "api.movielist_movies",
        "pk": 8,
        "fields": {
            "movielist": 1,
            "movie": 8
        }
    },
    {
        "model": "api.movielist_movies",
        "pk": 9,
        "fields": {
            "movielist": 1,
            "movie": 9
        }
    },
    {
        "model": "api.movielist_movies",
        "pk": 10,
        "fields": {
            "movielist": 1,
            "movie": 10
        }
    },
    {
        "model": "api.movielist_movies",
        "pk": 11,
        "fields": {
            "movielist": 1,
            "movie": 11
        }
    }
]